LICENSE
LICENSE.txt
README.rst
setup.cfg
setup.py
iamprayut/__init__.py
iamprayut/prayut.py
iamprayut.egg-info/PKG-INFO
iamprayut.egg-info/SOURCES.txt
iamprayut.egg-info/dependency_links.txt
iamprayut.egg-info/top_level.txt