Metadata-Version: 2.1
Name: iamprayut
Version: 0.0.2
Summary: Who is Prayut Chan-O-Cha
Home-page: https://github.com/Nissorn/iamprayut
Download-URL: https://github.com/Nissorn/iamprayut
Author: Prayut
Author-email: prayut@proton.me
License: MIT
Keywords: Prayut,Uncle Engineer
Classifier: Development Status :: 3 - Alpha
Classifier: Intended Audience :: Education
Classifier: Topic :: Utilities
Classifier: License :: OSI Approved :: MIT License
Classifier: Programming Language :: Python :: 3
Classifier: Programming Language :: Python :: 3.4
Classifier: Programming Language :: Python :: 3.5
Classifier: Programming Language :: Python :: 3.6
Classifier: Programming Language :: Python :: 3.7
Classifier: Programming Language :: Python :: 3.8
Classifier: Programming Language :: Python :: 3.9
Classifier: Programming Language :: Python :: 3.10
License-File: LICENSE
License-File: LICENSE.txt
